gt_converter/__init__.py
gt_converter/convert_coco.py
gt_converter/converter.py
gt_converter/utils.py
test/__init__.py
test/test_coco.py
gt_converter-0.1.0.dist-info/LICENSE
gt_converter-0.1.0.dist-info/METADATA
gt_converter-0.1.0.dist-info/WHEEL
gt_converter-0.1.0.dist-info/top_level.txt
gt_converter-0.1.0.dist-info/RECORD
